datason/__init__.py
datason/api.py
datason/cache_manager.py
datason/config.py
datason/converters.py
datason/core_new.py
datason/data_utils.py
datason/datetime_utils.py
datason/deserializers_new.py
datason/integrity.py
datason/json.py
datason/ml_serializers.py
datason/ml_type_handlers.py
datason/pickle_bridge.py
datason/redaction.py
datason/serializers.py
datason/type_handlers.py
datason/type_registry.py
datason/utils.py
datason/validation.py
datason-0.12.0.dist-info/METADATA
datason-0.12.0.dist-info/WHEEL
datason-0.12.0.dist-info/licenses/LICENSE
datason-0.12.0.dist-info/RECORD
