Metadata-Version: 2.4
Name: datason
Version: 0.12.0
Summary: A comprehensive Python package for intelligent serialization that handles complex data types with ease.
Project-URL: Homepage, https://github.com/danielendler/datason
Project-URL: Documentation, https://datason.readthedocs.io
Project-URL: Repository, https://github.com/danielendler/datason
Project-URL: Bug Tracker, https://github.com/danielendler/datason/issues
Project-URL: Changelog, https://github.com/danielendler/datason/blob/main/CHANGELOG.md
Project-URL: Discussions, https://github.com/danielendler/datason/discussions
Project-URL: Funding, https://github.com/sponsors/danielendler
Author: datason Contributors
Maintainer-email: datason Maintainers <maintainers@datason.dev>
License-Expression: MIT
License-File: LICENSE
Keywords: ai,data-science,datetime,json,ml,numpy,pandas,serialization
Classifier: Development Status :: 4 - Beta
Classifier: Intended Audience :: Developers
Classifier: Intended Audience :: Science/Research
Classifier: License :: OSI Approved :: MIT License
Classifier: Operating System :: OS Independent
Classifier: Programming Language :: Python :: 3
Classifier: Programming Language :: Python :: 3.8
Classifier: Programming Language :: Python :: 3.9
Classifier: Programming Language :: Python :: 3.10
Classifier: Programming Language :: Python :: 3.11
Classifier: Programming Language :: Python :: 3.12
Classifier: Programming Language :: Python :: 3.13
Classifier: Topic :: Internet :: WWW/HTTP :: Dynamic Content
Classifier: Topic :: Scientific/Engineering :: Artificial Intelligence
Classifier: Topic :: Scientific/Engineering :: Information Analysis
Classifier: Topic :: Software Development :: Libraries :: Python Modules
Classifier: Topic :: Utilities
Classifier: Typing :: Typed
Requires-Python: >=3.8
Provides-Extra: all
Requires-Dist: catboost>=1.2.0; extra == 'all'
Requires-Dist: cryptography>=42.0.0; extra == 'all'
Requires-Dist: numpy>=1.21.0; extra == 'all'
Requires-Dist: optuna>=3.0.0; extra == 'all'
Requires-Dist: pandas>=1.3.0; extra == 'all'
Requires-Dist: pillow>=9.0.0; extra == 'all'
Requires-Dist: plotly>=5.0.0; extra == 'all'
Requires-Dist: polars>=0.20.0; extra == 'all'
Requires-Dist: scikit-learn>=1.1.0; extra == 'all'
Requires-Dist: scipy>=1.9.0; extra == 'all'
Requires-Dist: tensorflow>=2.10.0; extra == 'all'
Requires-Dist: torch>=1.12.0; extra == 'all'
Provides-Extra: crypto
Requires-Dist: cryptography>=42.0.0; extra == 'crypto'
Provides-Extra: dev
Requires-Dist: bandit[toml]>=1.7.5; extra == 'dev'
Requires-Dist: build>=1.0.3; extra == 'dev'
Requires-Dist: hatch>=1.7.0; extra == 'dev'
Requires-Dist: mkdocs-gen-files>=0.5.0; extra == 'dev'
Requires-Dist: mkdocs-literate-nav>=0.6.1; extra == 'dev'
Requires-Dist: mkdocs-material>=9.4.0; extra == 'dev'
Requires-Dist: mkdocs>=1.5.3; extra == 'dev'
Requires-Dist: mkdocstrings[python]>=0.23.0; extra == 'dev'
Requires-Dist: mypy>=1.6.0; extra == 'dev'
Requires-Dist: pip-audit>=2.6.1; extra == 'dev'
Requires-Dist: pip-tools>=7.3.0; extra == 'dev'
Requires-Dist: pre-commit>=3.5.0; extra == 'dev'
Requires-Dist: pytest-benchmark>=4.0.0; extra == 'dev'
Requires-Dist: pytest-cov>=4.1.0; extra == 'dev'
Requires-Dist: pytest-xdist>=3.3.0; extra == 'dev'
Requires-Dist: pytest>=7.4.0; extra == 'dev'
Requires-Dist: ruff>=0.1.6; extra == 'dev'
Requires-Dist: safety>=2.3.5; extra == 'dev'
Requires-Dist: semgrep>=1.45.0; extra == 'dev'
Requires-Dist: twine>=4.0.2; extra == 'dev'
Requires-Dist: types-requests>=2.31.0; extra == 'dev'
Provides-Extra: docs
Requires-Dist: mkdocs-gen-files>=0.5.0; extra == 'docs'
Requires-Dist: mkdocs-literate-nav>=0.6.1; extra == 'docs'
Requires-Dist: mkdocs-material>=9.4.0; extra == 'docs'
Requires-Dist: mkdocs>=1.5.3; extra == 'docs'
Requires-Dist: mkdocstrings[python]>=0.23.0; extra == 'docs'
Provides-Extra: ml
Requires-Dist: catboost>=1.2.0; extra == 'ml'
Requires-Dist: optuna>=3.0.0; extra == 'ml'
Requires-Dist: pillow>=9.0.0; extra == 'ml'
Requires-Dist: plotly>=5.0.0; extra == 'ml'
Requires-Dist: polars>=0.20.0; extra == 'ml'
Requires-Dist: scikit-learn>=1.1.0; extra == 'ml'
Requires-Dist: scipy>=1.9.0; extra == 'ml'
Requires-Dist: tensorflow>=2.10.0; extra == 'ml'
Requires-Dist: torch>=1.12.0; extra == 'ml'
Provides-Extra: ml-extra
Requires-Dist: jax[cpu]>=0.4.0; extra == 'ml-extra'
Requires-Dist: keras>=3.0.0; extra == 'ml-extra'
Requires-Dist: transformers>=4.20.0; extra == 'ml-extra'
Provides-Extra: numpy
Requires-Dist: numpy>=1.21.0; extra == 'numpy'
Provides-Extra: pandas
Requires-Dist: pandas>=1.3.0; extra == 'pandas'
